alx_tool/__init__.py
alx_tool/__main__.py
alx_tool/config.py
alx_tool/spider.py
alx_tool/utils.py
alx_tool/version.py
alx_tool-2.0.0.dist-info/AUTHORS
alx_tool-2.0.0.dist-info/LICENSE
alx_tool-2.0.0.dist-info/METADATA
alx_tool-2.0.0.dist-info/WHEEL
alx_tool-2.0.0.dist-info/entry_points.txt
alx_tool-2.0.0.dist-info/top_level.txt
alx_tool-2.0.0.dist-info/RECORD
