Metadata-Version: 2.1
Name: alx-tool
Version: 2.0.0
Summary: A Python package for automating ALX School tasks.
Home-page: https://github.com/AmonMunyai/alx-tool
Author: Amon Munyai
Author-email: Amonmunyai11@gmail.com
Classifier: License :: OSI Approved :: MIT License
Classifier: Programming Language :: Python :: 3
Classifier: Programming Language :: Python :: 3.6
Classifier: Programming Language :: Python :: 3.7
Classifier: Programming Language :: Python :: 3.8
Classifier: Programming Language :: Python :: 3.9
Classifier: Programming Language :: Python :: 3.10
License-File: LICENSE
License-File: AUTHORS
Requires-Dist: scrapy ==2.5.1
Requires-Dist: cryptography ==3.4.8
